cabean_setup.py
cabean/__init__.py
cabean/debug.py
cabean/iface.py
cabean-1.0.dist-info/METADATA
cabean-1.0.dist-info/WHEEL
cabean-1.0.dist-info/top_level.txt
cabean-1.0.dist-info/RECORD
